aiosm/__init__.py
aiosm/__main__.py
aiosm/clinet.py
aiosm/dprint.py
aiosm/host.py
aiosm/node.py
aiosm/radio.py
aiosm/responder.py
aiosm-0.0.6.dist-info/entry_points.txt
aiosm-0.0.6.dist-info/WHEEL
aiosm-0.0.6.dist-info/METADATA
aiosm-0.0.6.dist-info/RECORD
