Metadata-Version: 2.1
Name: aiosm
Version: 0.0.6
Summary: An asynchronous network hub
Author-email: Callum B-C <callum@fish.cat>
Requires-Python: >=3.8
Classifier: Intended Audience :: Developers
Classifier: License :: OSI Approved :: MIT License
Classifier: Programming Language :: Python :: 3
Classifier: Topic :: Software Development :: Libraries :: Python Modules
Requires-Dist: sphinx ; extra == "doc"
Requires-Dist: pytest ; extra == "test"
Requires-Dist: pytest-cov ; extra == "test"
Project-URL: Source, https://github.com/C-Bookie/aiosm
Provides-Extra: doc
Provides-Extra: test
